src/__init__.py
src/enhanced_logger.py
loggio-2025.12.14.dist-info/METADATA
loggio-2025.12.14.dist-info/WHEEL
loggio-2025.12.14.dist-info/licenses/LICENSE
loggio-2025.12.14.dist-info/RECORD
