Metadata-Version: 2.4
Name: loggio
Version: 2025.12.14
Summary: Comprehensive logging utility with colored output, user context tracking, and automatic truncation.
Project-URL: Homepage, https://github.com/xcollantes/loggio
Project-URL: Repository, https://github.com/xcollantes/loggio
Project-URL: Issues, https://github.com/xcollantes/loggio/issues
Author-email: Xavier Collantes <collantes.xavier@gmail.com>
Maintainer-email: Xavier Collantes <collantes.xavier@gmail.com>
License-Expression: CC0-1.0
License-File: LICENSE
Keywords: automatic truncation,colored,debugging,enhanced,logger,logging,terminal,user context
Classifier: Development Status :: 4 - Beta
Classifier: Environment :: Console
Classifier: Intended Audience :: Developers
Classifier: License :: CC0 1.0 Universal (CC0 1.0) Public Domain Dedication
Classifier: Programming Language :: Python :: 3
Classifier: Programming Language :: Python :: 3.10
Classifier: Programming Language :: Python :: 3.11
Classifier: Programming Language :: Python :: 3.12
Classifier: Topic :: System :: Logging
Requires-Python: >=3.10
Provides-Extra: dev
Requires-Dist: pytest-cov>=4.0.0; extra == 'dev'
Requires-Dist: pytest>=7.0.0; extra == 'dev'
